{
    "header": {
        "metadata": [
            {
                "metaName": "adskFileFormatVersion",
                "metaValue": "100L"
            }
        ]
    },
    "namespaces": [],
    "types": [],
    "compounds": [
        {
            "name": "Hyuu::String::pad_string",
            "uriImported": "stream:/stream",
            "metadata": [
                {
                    "metaName": "io_nodes",
                    "metadata": [
                        {
                            "metaName": "io_inodes",
                            "metadata": [
                                {
                                    "metaName": "input",
                                    "metadata": [
                                        {
                                            "metaName": "DisplayMode",
                                            "metaType": "string",
                                            "metaValue": "2"
                                        },
                                        {
                                            "metaName": "LayoutPos",
                                            "metaType": "string",
                                            "metaValue": "-708.374 -96.431"
                                        },
                                        {
                                            "metaName": "io_ports",
                                            "metadata": [
                                                {
                                                    "metaName": "string"
                                                },
                                                {
                                                    "metaName": "padding"
                                                },
                                                {
                                                    "metaName": "pad_character"
                                                }
                                            ]
                                        },
                                        {
                                            "metaName": "zValue",
                                            "metaType": "string",
                                            "metaValue": "31.000000"
                                        }
                                    ]
                                },
                                {
                                    "metaName": "input1",
                                    "metadata": [
                                        {
                                            "metaName": "LayoutPos",
                                            "metaType": "string",
                                            "metaValue": "877 -322"
                                        },
                                        {
                                            "metaName": "DisplayMode",
                                            "metaType": "string",
                                            "metaValue": "2"
                                        },
                                        {
                                            "metaName": "zValue",
                                            "metaType": "string",
                                            "metaValue": "47.000000"
                                        },
                                        {
                                            "metaName": "io_ports",
                                            "metadata": [
                                                {
                                                    "metaName": "front"
                                                }
                                            ]
                                        }
                                    ]
                                }
                            ]
                        },
                        {
                            "metaName": "io_onodes",
                            "metadata": [
                                {
                                    "metaName": "output",
                                    "metadata": [
                                        {
                                            "metaName": "DisplayMode",
                                            "metaType": "string",
                                            "metaValue": "2"
                                        },
                                        {
                                            "metaName": "io_ports",
                                            "metadata": [
                                                {
                                                    "metaName": "out_string"
                                                }
                                            ]
                                        },
                                        {
                                            "metaName": "zValue",
                                            "metaType": "string",
                                            "metaValue": "39.000000"
                                        },
                                        {
                                            "metaName": "LayoutPos",
                                            "metaType": "string",
                                            "metaValue": "1734.44 -181.409"
                                        }
                                    ]
                                }
                            ]
                        }
                    ]
                },
                {
                    "metaName": "ViewportRect",
                    "metaType": "string",
                    "metaValue": "-434.997 -484.816 2425.4 1156.33"
                },
                {
                    "metaName": "DisplayMode",
                    "metaType": "string",
                    "metaValue": "2"
                },
                {
                    "metaName": "zValue",
                    "metaType": "string",
                    "metaValue": "300.000000"
                },
                {
                    "metaName": "LayoutPos",
                    "metaType": "string",
                    "metaValue": "1762.97 590.693"
                },
                {
                    "metaName": "documentation",
                    "metaType": "string",
                    "metaValue": "../../documentation/core/String/pad_string.md"
                },
                {
                    "metaName": "icon",
                    "metaType": "string",
                    "metaValue": "../../icons/hyuu_icon.png"
                }
            ],
            "ports": [
                {
                    "portName": "string",
                    "portDirection": "input",
                    "portType": "string",
                    "portDefault": ""
                },
                {
                    "portName": "padding",
                    "portDirection": "input",
                    "portType": "long",
                    "portDefault": "4"
                },
                {
                    "portName": "out_string",
                    "portDirection": "output",
                    "portType": "string"
                },
                {
                    "portName": "pad_character",
                    "portDirection": "input",
                    "portType": "string",
                    "portDefault": "0"
                },
                {
                    "portName": "front",
                    "portDirection": "input",
                    "portType": "bool",
                    "portDefault": "true"
                }
            ],
            "compoundNodes": [
                {
                    "nodeName": "string_length",
                    "nodeType": "Core::String::string_length",
                    "metadata": [
                        {
                            "metaName": "DisplayMode",
                            "metaType": "string",
                            "metaValue": "2"
                        },
                        {
                            "metaName": "LayoutPos",
                            "metaType": "string",
                            "metaValue": "-33.5226 3.1543"
                        },
                        {
                            "metaName": "zValue",
                            "metaType": "string",
                            "metaValue": "37.000000"
                        }
                    ]
                },
                {
                    "nodeName": "subtract",
                    "nodeType": "Core::Math::subtract",
                    "multiInPortNames": [
                        "padding",
                        "length"
                    ],
                    "metadata": [
                        {
                            "metaName": "DisplayMode",
                            "metaType": "string",
                            "metaValue": "2"
                        },
                        {
                            "metaName": "LayoutPos",
                            "metaType": "string",
                            "metaValue": "220.61 256.628"
                        },
                        {
                            "metaName": "zValue",
                            "metaType": "string",
                            "metaValue": "32.000000"
                        }
                    ]
                },
                {
                    "nodeName": "if",
                    "nodeType": "Core::Logic::if",
                    "metadata": [
                        {
                            "metaName": "DisplayMode",
                            "metaType": "string",
                            "metaValue": "2"
                        },
                        {
                            "metaName": "zValue",
                            "metaType": "string",
                            "metaValue": "40.000000"
                        },
                        {
                            "metaName": "LayoutPos",
                            "metaType": "string",
                            "metaValue": "1462.85 -230.54"
                        }
                    ]
                },
                {
                    "nodeName": "greater_or_equal",
                    "nodeType": "Core::Logic::greater_or_equal",
                    "metadata": [
                        {
                            "metaName": "DisplayMode",
                            "metaType": "string",
                            "metaValue": "2"
                        },
                        {
                            "metaName": "LayoutPos",
                            "metaType": "string",
                            "metaValue": "515.409 -127.194"
                        },
                        {
                            "metaName": "zValue",
                            "metaType": "string",
                            "metaValue": "36.000000"
                        }
                    ]
                },
                {
                    "nodeName": "resize_array",
                    "nodeType": "Core::Array::resize_array",
                    "metadata": [
                        {
                            "metaName": "DisplayMode",
                            "metaType": "string",
                            "metaValue": "2"
                        },
                        {
                            "metaName": "LayoutPos",
                            "metaType": "string",
                            "metaValue": "525.515 223.611"
                        },
                        {
                            "metaName": "zValue",
                            "metaType": "string",
                            "metaValue": "33.000000"
                        }
                    ]
                },
                {
                    "nodeName": "build_string",
                    "nodeType": "Core::String::build_string",
                    "fanInPortNames": {
                        "strings": [
                            "resized",
                            "string"
                        ]
                    },
                    "metadata": [
                        {
                            "metaName": "DisplayMode",
                            "metaType": "string",
                            "metaValue": "2"
                        },
                        {
                            "metaName": "PortExpandedState",
                            "metadata": [
                                {
                                    "metaName": "strings",
                                    "metaType": "string",
                                    "metaValue": "1"
                                }
                            ]
                        },
                        {
                            "metaName": "zValue",
                            "metaType": "string",
                            "metaValue": "43.000000"
                        },
                        {
                            "metaName": "LayoutPos",
                            "metaType": "string",
                            "metaValue": "864.801 180.661"
                        }
                    ]
                },
                {
                    "nodeName": "if1",
                    "nodeType": "Core::Logic::if",
                    "metadata": [
                        {
                            "metaName": "DisplayMode",
                            "metaType": "string",
                            "metaValue": "2"
                        },
                        {
                            "metaName": "zValue",
                            "metaType": "string",
                            "metaValue": "42.000000"
                        },
                        {
                            "metaName": "LayoutPos",
                            "metaType": "string",
                            "metaValue": "1317.22 90.1461"
                        }
                    ]
                },
                {
                    "nodeName": "build_string1",
                    "nodeType": "Core::String::build_string",
                    "fanInPortNames": {
                        "strings": [
                            "string",
                            "resized"
                        ]
                    },
                    "metadata": [
                        {
                            "metaName": "DisplayMode",
                            "metaType": "string",
                            "metaValue": "2"
                        },
                        {
                            "metaName": "PortExpandedState",
                            "metadata": [
                                {
                                    "metaName": "strings",
                                    "metaType": "string",
                                    "metaValue": "1"
                                }
                            ]
                        },
                        {
                            "metaName": "zValue",
                            "metaType": "string",
                            "metaValue": "46.000000"
                        },
                        {
                            "metaName": "LayoutPos",
                            "metaType": "string",
                            "metaValue": "890.123 421.837"
                        }
                    ]
                }
            ],
            "connections": [
                {
                    "source": ".padding",
                    "target": "subtract.first.padding"
                },
                {
                    "source": "string_length.length",
                    "target": "subtract.first.length"
                },
                {
                    "source": "if.output",
                    "target": ".out_string"
                },
                {
                    "source": "string_length.length",
                    "target": "greater_or_equal.first"
                },
                {
                    "source": ".padding",
                    "target": "greater_or_equal.second"
                },
                {
                    "source": "greater_or_equal.output",
                    "target": "if.condition"
                },
                {
                    "source": "subtract.output",
                    "target": "resize_array.new_size"
                },
                {
                    "source": "resize_array.resized",
                    "target": "build_string.strings.resized"
                },
                {
                    "source": ".pad_character",
                    "target": "resize_array.default"
                },
                {
                    "source": ".string",
                    "target": "string_length.string"
                },
                {
                    "source": ".string",
                    "target": "build_string.strings.string"
                },
                {
                    "source": ".string",
                    "target": "if.true_case"
                },
                {
                    "source": "build_string.joined",
                    "target": "if1.true_case"
                },
                {
                    "source": ".string",
                    "target": "build_string1.strings.string"
                },
                {
                    "source": "resize_array.resized",
                    "target": "build_string1.strings.resized"
                },
                {
                    "source": "build_string1.joined",
                    "target": "if1.false_case"
                },
                {
                    "source": ".front",
                    "target": "if1.condition"
                },
                {
                    "source": "if1.output",
                    "target": "if.false_case"
                }
            ],
            "values": [
                {
                    "valueName": "resize_array.default",
                    "valueType": "string",
                    "value": "0"
                }
            ],
            "reservedNodeNames": [
                {
                    "name": "input"
                },
                {
                    "name": "output"
                },
                {
                    "name": "input1"
                }
            ]
        }
    ]
}